network_docopt.py
network_docopt-0.1.10.data/scripts/network-docopt-example
network_docopt-0.1.10.data/data/usr/share/bash-completion/completions/network-docopt-example
network_docopt-0.1.10.dist-info/METADATA
network_docopt-0.1.10.dist-info/RECORD
network_docopt-0.1.10.dist-info/metadata.json
network_docopt-0.1.10.dist-info/WHEEL
network_docopt-0.1.10.dist-info/DESCRIPTION.rst
network_docopt-0.1.10.dist-info/top_level.txt
