Metadata-Version: 2.0
Name: network-docopt
Version: 0.1.10
Summary: Network Docopt
Home-page: https://github.com/CumulusNetworks/NetworkDocopt
Author: Cumulus Networks
Author-email: ce-ceng@cumulusnetworks.com
License: MIT
Platform: UNKNOWN
Classifier: License :: OSI Approved :: MIT License
Classifier: Development Status :: 4 - Beta
Classifier: Operating System :: POSIX :: Linux
Classifier: Topic :: System :: Networking
Classifier: Topic :: Utilities
Classifier: License :: OSI Approved :: MIT License
Requires-Dist: ipaddr
